Alu.v
//----------------------------------------------------------------------------------
// Design Name: Alu
// Function: Executes six types of operations, and, or, add, nor, xor and sub.
//----------------------------------------------------------------------------------
module Alu (
    input [31:0] a,
	input [31:0] b,
	output [31:0] aluout,
	input [2:0] op,
	input unsig,
	output compout,
	output overflow
);
	reg compout, overflow, aluout;
	always @(*) begin
		
		if(unsig == 1) begin
			compout<=(a<b?1:0);
		end else begin
			compout<=($signed(a)<$signed(b) ? 1:0); // http://excamera.com/sphinx/fpga-verilog-sign.html
		end

		case(op)
			3'b000:begin
				//AND
				aluout<=($signed(a)&$signed(b));
				overflow<=0;
			end
			
			3'b001:begin
				//OR
				aluout<=(a|b);
				overflow<=0;
			end
			
			3'b010:begin
				//ADD
				if(unsig == 1) begin
					aluout = (a+b);
				end else begin
					aluout = ($signed(a)+$signed(b));
				end

				if($signed(a) >= 0 && $signed(b) >= 0) begin
					overflow = ($signed(aluout) < 0 ? 1 : 0);
				end else begin
					if($signed(a) < 0 && $signed(b) < 0) begin
						overflow = ($signed(aluout)>=0 ? 1 : 0);
					end
				end
			end
			
			3'b100:begin
				//NOR
				aluout<=(a~|b);
				overflow<=0;
			end
			
			3'b101:begin
				//XOR
				aluout<=(a^b);
				overflow<=0;
			end
			
			3'b110:begin
				//SUB
				if(unsig == 1) begin
					aluout = (a-b);
				end else begin
					aluout = ($signed(a)-$signed(b));
				end

				if($signed(a)>=0 && $signed(b)<0) begin
					overflow <= (aluout<0 ? 1 : 0);
				end else begin
					if($signed(a)<0 && $signed(b)>=0)begin
						overflow <= (aluout>=0 ? 1 : 0);
					end
				end
			end
			
			default:begin
				aluout<=0;
				overflow<=0;
			end
		endcase
	end

endmodule

tb_Alu.v
//----------------------------------------------------------------------------------
// Design Name: tb_Alu.
// Function: Test if the output of all operations is what is expected to be.
//----------------------------------------------------------------------------------
module tb_Alu;
	reg [31:0] a;
	reg [31:0] b;
	reg [2:0] op;
	reg unsig;
	wire compout;
	wire overflow;
	wire [31:0] aluout;

	Alu tb(a, b, aluout, op, unsig, compout, overflow);
	initial begin
		$dumpfile("result.vcd");
		$dumpvars(0, tb_Alu);
	
		a = 32'b11111111111111111111111111111011;
		b = 32'b11111111111111111111111111111100;
		unsig = 1;
		op = 3'b000;
		#10;
		$display("Result: %d %d %d\n", a, b, aluout);

		//Neste teste overflow tem que ser 1(um)
		$display("Teste para overflow: Neste teste o sinal de overflow tem que ser 1(um)");
		a = 32'b01111111111111111111111111111111;
		b = 32'b01111111111111111111111111111111;
        op = 3'b010;
		unsig = 0;
		$display("a = %b\nb = %b\nop = %b", a, b, op);
		#10;
		$display("Result: compout=%b  overflow=%b  aluout=%b\n\n", compout, overflow, aluout);

		//Neste teste, overflow tem que ser 0(zero)
		$display("Teste para overflow: Neste teste o sinal de overflow tem que ser 0(zero)");
		a = 32'b01000011011001100111000100000111;
		b = 32'b00001100110001100100011001111000;
        op = 3'b010;
		unsig = 0;
		$display("a = %b\nb = %b\nop = %b", a, b, op);
		#10;
		$display("Result: compout=%b  overflow=%b  aluout=%b\n\n", compout, overflow, aluout);
		
		
		//INICIO TESTE OPERACOES
		$display("Teste das operações:\n");
		$display("AND");
		a = 32'b01000011011001100111000100000111;
		b = 32'b00001100110001100100011001111000;
        op = 3'b000;
		unsig = 0;
		$display("a = %b\nb = %b\nop = %b", a, b, op);
		#10;
		$display("Result: compout=%b  overflow=%b  aluout=%b\n\n", compout, overflow, aluout);
		
		
		$display("OR");
		a = 32'b01000011011001100111000100000111;
		b = 32'b00001100110001100100011001111000;
        op = 3'b001;
		unsig = 0;
		$display("a = %b\nb = %b\nop = %b", a, b, op);
		#10;
		$display("Result: compout=%b  overflow=%b  aluout=%b\n\n", compout, overflow, aluout);
	

		$display("ADD");
		a = 32'b01000011011001100111000100000111;
		b = 32'b00001100110001100100011001111000;
        op = 3'b010;
		unsig = 0;
		$display("a = %b\nb = %b\nop = %b", a, b, op);
		#10;
		$display("Result: compout=%b  overflow=%b  aluout=%b\n\n", compout, overflow, aluout);
		

		$display("NOR");
		a = 32'b01000011011001100111000100000111;
		b = 32'b00001100110001100100011001111000;
        op = 3'b100;
		unsig = 0;
		$display("a = %b\nb = %b\nop = %b", a, b, op);
		#10;
		$display("Result: compout=%b  overflow=%b  aluout=%b\n\n", compout, overflow, aluout);
		

		$display("XOR");
		a = 32'b01000011011001100111000100000111;
		b = 32'b00001100110001100100011001111000;
        op = 3'b101;
		unsig = 0;
		$display("a = %b\nb = %b\nop = %b", a, b, op);
		#10;
		$display("Result: compout=%b  overflow=%b  aluout=%b\n\n", compout, overflow, aluout);
		
		
		$display("SUB");
		a = 32'b01000011011001100111000100000111;
		b = 32'b00001100110001100100011001111000;
        op = 3'b110;
		unsig = 0;
		$display("a = %b\nb = %b\nop = %b", a, b, op);
		#10;
		$display("Result: compout=%b  overflow=%b  aluout=%b\n\n", compout, overflow, aluout);
		//END TESTE OPERACOES
	end
endmodule

result.vcd
$date
	Tue Mar 11 23:45:59 2014
$end
$version
	Icarus Verilog
$end
$timescale
	1s
$end
$scope module tb_Alu $end
$var wire 32 ! aluout [31:0] $end
$var wire 1 " compout $end
$var wire 1 # overflow $end
$var reg 32 $ a [31:0] $end
$var reg 32 % b [31:0] $end
$var reg 3 & op [2:0] $end
$var reg 1 ' unsig $end
$scope module tb $end
$var wire 32 ( a [31:0] $end
$var wire 32 ) b [31:0] $end
$var wire 3 * op [2:0] $end
$var wire 1 + unsig $end
$var reg 32 , aluout [31:0] $end
$var reg 1 - compout $end
$var reg 1 . overflow $end
$upscope $end
$upscope $end
$enddefinitions $end
#0
$dumpvars
0.
1-
b11111111111111111111111111111000 ,
1+
b0 *
b11111111111111111111111111111100 )
b11111111111111111111111111111011 (
1'
b0 &
b11111111111111111111111111111100 %
b11111111111111111111111111111011 $
0#
1"
b11111111111111111111111111111000 !
$end
#10
0-
0"
1.
1#
b11111111111111111111111111111110 ,
b11111111111111111111111111111110 !
0'
0+
b10 &
b10 *
b1111111111111111111111111111111 %
b1111111111111111111111111111111 )
b1111111111111111111111111111111 $
b1111111111111111111111111111111 (
#20
0.
0#
b1010000001011001011011101111111 ,
b1010000001011001011011101111111 !
b1100110001100100011001111000 %
b1100110001100100011001111000 )
b1000011011001100111000100000111 $
b1000011011001100111000100000111 (
#30
b10001100100000000000000 ,
b10001100100000000000000 !
b0 &
b0 *
#40
b1001111111001100111011101111111 ,
b1001111111001100111011101111111 !
b1 &
b1 *
#50
b1010000001011001011011101111111 ,
b1010000001011001011011101111111 !
b10 &
b10 *
#60
b10110000000110011000100010000000 ,
b10110000000110011000100010000000 !
b100 &
b100 *
#70
b1001111101000000011011101111111 ,
b1001111101000000011011101111111 !
b101 &
b101 *
#80
b110110101000000010101010001111 ,
b110110101000000010101010001111 !
b110 &
b110 *
